confidentialmindserver/__init__.py
confidentialmindserver/config_manager.py
confidentialmindserver/config_manager_streamlit.py
confidentialmindserver-0.1.1.dist-info/LICENSE
confidentialmindserver-0.1.1.dist-info/METADATA
confidentialmindserver-0.1.1.dist-info/NOTICE
confidentialmindserver-0.1.1.dist-info/WHEEL
confidentialmindserver-0.1.1.dist-info/top_level.txt
confidentialmindserver-0.1.1.dist-info/RECORD
