Metadata-Version: 2.1
Name: confidentialmindserver
Version: 0.1.1
Summary: Core functionality for interfacing with the ConfidentialMind stack
Author-email: confidentialmind <info@confidentialmind.com>
License: Apache-2.0
Project-URL: Homepage, https://www.confidentialmind.com/
Classifier: Programming Language :: Python :: 3
Classifier: License :: OSI Approved :: Apache Software License
Classifier: Operating System :: OS Independent
Requires-Python: >=3.10
License-File: LICENSE
License-File: NOTICE
Requires-Dist: pydantic >=2.2
Requires-Dist: websockets >=12.0
Requires-Dist: requests >=2.32.2
